arcaptcha_python/Arcaptcha.py
arcaptcha_python/__init__.py
arcaptcha_python-0.1.2.dist-info/LICENSE
arcaptcha_python-0.1.2.dist-info/METADATA
arcaptcha_python-0.1.2.dist-info/WHEEL
arcaptcha_python-0.1.2.dist-info/top_level.txt
arcaptcha_python-0.1.2.dist-info/RECORD
