Metadata-Version: 2.1
Name: arcaptcha-python
Version: 0.1.2
Summary: Python package for Arcaptcha
Author: ARCaptcha
Author-email: info@arcaptcha.ir
Keywords: captcha,api,arcaptcha
License-File: LICENSE
Requires-Dist: requests
